MANIFEST.in
README.rst
setup.py
dist/django-quickedit-0.1.0.tar.gz
django_quickedit.egg-info/PKG-INFO
django_quickedit.egg-info/SOURCES.txt
django_quickedit.egg-info/dependency_links.txt
django_quickedit.egg-info/top_level.txt
example/app/__init__.py
example/app/admin.py
example/app/models.py
example/app/tests.py
example/app/views.py
quickedit/__init__.py
quickedit/admin.py
quickedit/templates/quickedit/change_list.html
quickedit/templates/quickedit/change_list_results.html
quickedit/templatetags/__init__.py
quickedit/templatetags/quickedit.py