Metadata-Version: 1.0
Name: django-quickedit
Version: 0.1.1
Summary: Quick editing of fields in the django admin
Home-page: http://github.com/washingtontimes/django-quickedit
Author: Justin Quick
Author-email: justquick@gmail.com
License: UNKNOWN
Platform: UNKNOWN
Classifier: Development Status :: 4 - Beta
Classifier: Environment :: Web Environment
Classifier: Framework :: Django
Classifier: License :: OSI Approved :: Apache Software License
